normtransform/JonesPewseyTransformation.cpp
normtransform/LogSinhTransformation.cpp
normtransform/SinhAsinhTransformation.cpp
normtransform/Transformation.cpp
normtransform/Transformation.h
normtransform/YeoJohnsonTransformation.cpp
normtransform/__init__.py
normtransform/demo.py
normtransform/dummy_trans.py
normtransform/pytrans.cp312-win_amd64.pyd
normtransform/pytrans.cpp
normtransform-0.2.0.dist-info/METADATA
normtransform-0.2.0.dist-info/WHEEL
normtransform-0.2.0.dist-info/top_level.txt
normtransform-0.2.0.dist-info/RECORD
