Metadata-Version: 2.4
Name: normtransform
Version: 0.2.0
Summary: Transformation for normalising data
Author-email: Andrew Schepen <andrew.schepen@csiro.au>
License: MIT
Requires-Python: <3.14,>=3.11
Requires-Dist: numpy>=2.2.5
Requires-Dist: cython>=3.0.12
Requires-Dist: pandas>=2.2.3
Requires-Dist: scipy>=1.15.2
Requires-Dist: setuptools>=79.0.1
Requires-Dist: pytest<9.0.0,>=8.3.5
Requires-Dist: twine<7.0.0,>=6.1.0
Requires-Dist: cibuildwheel<3.0.0,>=2.23.3
Requires-Dist: matplotlib<4.0.0,>=3.10.3
Provides-Extra: test
Requires-Dist: pytest; extra == "test"
Requires-Dist: pytest-cov; extra == "test"
